pysm/__init__.py
pysm/pysm.py
pysm/version.py
upysm-0.3.4.dist-info/LICENSE
upysm-0.3.4.dist-info/METADATA
upysm-0.3.4.dist-info/WHEEL
upysm-0.3.4.dist-info/top_level.txt
upysm-0.3.4.dist-info/RECORD
